reserving/__about__.py
reserving/__init__.py
reserving-0.0.dev0.dist-info/METADATA
reserving-0.0.dev0.dist-info/WHEEL
reserving-0.0.dev0.dist-info/licenses/LICENSE
reserving-0.0.dev0.dist-info/RECORD
