Metadata-Version: 2.3
Name: reserving
Version: 0.0.dev0
Summary: Reserving methods for non-life insurance
Project-URL: Homepage, https://github.com/lorentzenchr/reserving
Project-URL: Source, https://github.com/lorentzenchr/reserving
Project-URL: Tracker, https://github.com/lorentzenchr/reserving/issues
Author-email: Christian Lorentzen <lorentzen.ch@gmail.com>
License: MIT License
Keywords: actuarial reserving,machine learning
Classifier: Development Status :: 1 - Planning
Classifier: Framework :: Hatch
Classifier: License :: OSI Approved :: MIT License
Classifier: Operating System :: OS Independent
Classifier: Programming Language :: Python :: 3
Classifier: Topic :: Scientific/Engineering
Requires-Python: >=3.10
Requires-Dist: numpy>=2.1.3
Requires-Dist: packaging>=24.2
Requires-Dist: polars>=1.10.0
